Metadata-Version: 2.1
Name: odoo12-addon-account-move-template
Version: 12.0.1.1.0
Summary: Templates for recurring Journal Entries
Home-page: https://github.com/OCA/account-financial-tools
Author: Agile Business Group, Aurium Technologies, Vauxoo, Eficent, Akretion, Odoo Community Association (OCA)
Author-email: support@odoo-community.org
License: AGPL-3
Platform: UNKNOWN
Classifier: Programming Language :: Python
Classifier: Framework :: Odoo
Classifier: License :: OSI Approved :: GNU Affero General Public License v3
Requires-Python: >=3.5
Requires-Dist: odoo (<12.1dev,>=12.0a)
